{
  "generatedAt": "2026-06-18T07:12:39.136Z",
  "source": "KCIF",
  "listUrl": "https://www.kcif.or.kr/annual/monthlyList",
  "reports": [
    {
      "kind": "insight",
      "label": "국제금융 INSIGHT",
      "title": "[26.6월] 국제금융 INSIGHT",
      "date": "2026.06.16",
      "views": "412",
      "attachment": "국제금융 인사이트 `26.6월호.pdf",
      "url": "https://www.kcif.or.kr/annual/reportView?rpt_no=37201&mn=001004&pe=004001&skey=&sval=&pg=1&pp=10",
      "source": "KCIF",
      "focus": [
        "동향 & 전망: 세계경제, 국제ㆍ국내금융시장, 글로벌 은행산업",
        "국제금융센터의 시각: 글로벌 리스크 워치, 관심보고서 다시 읽기",
        "주요지표"
      ],
      "implication": "국제금융 INSIGHT는 미국 지표 중심의 FRED 판단에 글로벌 자금흐름과 정책 해석을 덧붙이는 보조 자료입니다."
    },
    {
      "kind": "riskWatch",
      "label": "글로벌 리스크 워치",
      "title": "[26.6월] 글로벌 리스크 워치",
      "date": "2026.06.05",
      "views": "629",
      "attachment": "260605-글로벌 리스크 워치.pdf",
      "url": "https://www.kcif.or.kr/annual/reportView?rpt_no=37160&mn=001004&pe=004008&skey=&sval=&pg=1&pp=10",
      "source": "KCIF",
      "focus": [
        "美vs이란간 협상 교착으로 '중동전쟁 장기화' 우려가 지속되는 가운데 고물가 고착화, 정책금리 인상, 국채수급 이슈가 부각되면서 선진국 장기금리가 5월 중 큰 폭 상승",
        "'선진국 금리 고수준'의 순위는 매월 상승하는 모습. 장기금리는 경기 등에 따른 결과적 변수이기도 하나 이례적으로 높은 현수준은 금융시장을 압박하는 독립적인 리스크로 작용",
        "개전 이후의 유가상승이 시차를 두고 물가를 높이고 성장을 둔화시킬 소지가 있어 일부국에서 '스태그플레이션 압력'의 발생 가능성이 증가할 우려",
        "물가, 실업률이 높은 서유럽과 원유 의존도가 높고 가계구매력이 약한 일부 신흥국들이 취약"
      ],
      "implication": "KCIF의 리스크 워치는 FRED 지표가 포착하지 못하는 지정학, 유가, 글로벌 금리, 신용 이벤트를 보완합니다."
    }
  ],
  "advice": [
    "장기금리 리스크가 부각될 때는 성장주, 리츠, 장기채처럼 듀레이션이 긴 자산의 비중 확대를 서두르지 않는 편이 낫습니다.",
    "유가와 물가 충격이 함께 언급되면 에너지, 원자재, 물가 방어력이 있는 현금흐름 기업을 우선 점검하고 항공·운송·재량소비는 보수적으로 봅니다.",
    "신흥국·달러 스트레스가 커질 때는 달러 방어 포지션과 미국 국채의 방어 역할을 같이 봅니다.",
    "INSIGHT가 세계경제, 금융시장, 은행산업을 점검축으로 제시할 때는 지수 방향보다 금리·신용·은행 유동성의 동시 악화 여부를 먼저 확인합니다."
  ]
}
